numeral_converter/__init__.py
numeral_converter/constants.py
numeral_converter/lang_data_loader.py
numeral_converter/numeral_converter.py
numeral_converter/text.py
numeral_converter/utils.py
numeral_converter-0.0.2.dist-info/LICENSE
numeral_converter-0.0.2.dist-info/WHEEL
numeral_converter-0.0.2.dist-info/METADATA
numeral_converter-0.0.2.dist-info/RECORD
