Metadata-Version: 2.1
Name: numeral-converter
Version: 0.0.2
Summary: 
Author: Tetiana Lytvynenko
Author-email: lytvynenkotv@gmail.com
Requires-Python: >=3.9,<4.0
Classifier: Programming Language :: Python :: 3
Classifier: Programming Language :: Python :: 3.9
Classifier: Programming Language :: Python :: 3.10
Classifier: Programming Language :: Python :: 3.11
Requires-Dist: fuzzy-multi-dict (>=0.0.4,<0.0.5)
Requires-Dist: pandas (>=1.5.3,<2.0.0)
Requires-Dist: semiotic-tricks-data-loader (>=0.0.1,<0.0.2)
